README.rst
setup.py
piianalyzer/__init__.py
piianalyzer/analyzer.py
piianalyzer.egg-info/PKG-INFO
piianalyzer.egg-info/SOURCES.txt
piianalyzer.egg-info/dependency_links.txt
piianalyzer.egg-info/pbr.json
piianalyzer.egg-info/requires.txt
piianalyzer.egg-info/top_level.txt
tests/__init__.py
tests/test_piianalyzer.py