Metadata-Version: 1.1
Name: piianalyzer
Version: 0.1.0
Summary: Analyzing PII in datasets
Home-page: https://github.com/github/piianalyzer
Author: Savio Abuga
Author-email: savioabuga@gmail.com
License: UNKNOWN
Platform: UNKNOWN
Classifier: Development Status :: 2 - Pre-Alpha
Classifier: Programming Language :: Python
Classifier: Programming Language :: Python :: 2
Classifier: Programming Language :: Python :: 2.7
Classifier: Programming Language :: Python :: 3
Classifier: Programming Language :: Python :: 3.4
